apache_atlas/__init__.py
apache_atlas/exceptions.py
apache_atlas/utils.py
apache_atlas/client/__init__.py
apache_atlas/client/admin.py
apache_atlas/client/base_client.py
apache_atlas/client/discovery.py
apache_atlas/client/entity.py
apache_atlas/client/glossary.py
apache_atlas/client/lineage.py
apache_atlas/client/relationship.py
apache_atlas/client/typedef.py
apache_atlas/model/__init__.py
apache_atlas/model/admin.py
apache_atlas/model/discovery.py
apache_atlas/model/enums.py
apache_atlas/model/glossary.py
apache_atlas/model/instance.py
apache_atlas/model/lineage.py
apache_atlas/model/misc.py
apache_atlas/model/profile.py
apache_atlas/model/relationship.py
apache_atlas/model/typedef.py
apache_atlas-0.0.16.dist-info/LICENSE
apache_atlas-0.0.16.dist-info/METADATA
apache_atlas-0.0.16.dist-info/WHEEL
apache_atlas-0.0.16.dist-info/top_level.txt
apache_atlas-0.0.16.dist-info/RECORD
