Metadata-Version: 2.1
Name: apache-atlas
Version: 0.0.16
Summary: Apache Atlas Python Client
Home-page: https://github.com/apache/atlas/tree/master/intg/src/main/python
Author: Apache Atlas
Author-email: dev@atlas.apache.org
License: Apache LICENSE 2.0
Keywords: atlas client,apache atlas
Classifier: Programming Language :: Python :: 3.6
Classifier: License :: OSI Approved :: Apache Software License
Classifier: Operating System :: OS Independent
Requires-Python: >=3.6
License-File: LICENSE
Requires-Dist: requests>=2.24
